setup.py
storm_gui/__init__.py
storm_gui/storm_gui.py
stormssh_gui.egg-info/PKG-INFO
stormssh_gui.egg-info/SOURCES.txt
stormssh_gui.egg-info/dependency_links.txt
stormssh_gui.egg-info/entry_points.txt
stormssh_gui.egg-info/requires.txt
stormssh_gui.egg-info/top_level.txt