Metadata-Version: 1.0
Name: stormssh-gui
Version: 0.3
Summary: a gui application form stormssh
Home-page: http://github.com/emre/storm-gui
Author: Emre Yilmaz
Author-email: mail@emreyilmaz.me
License: MIT
Platform: UNKNOWN
